langchain_openai/__init__.py
langchain_openai/py.typed
langchain_openai/chat_models/__init__.py
langchain_openai/chat_models/_client_utils.py
langchain_openai/chat_models/_compat.py
langchain_openai/chat_models/azure.py
langchain_openai/chat_models/base.py
langchain_openai/data/__init__.py
langchain_openai/data/_profiles.py
langchain_openai/data/profile_augmentations.toml
langchain_openai/embeddings/__init__.py
langchain_openai/embeddings/azure.py
langchain_openai/embeddings/base.py
langchain_openai/llms/__init__.py
langchain_openai/llms/azure.py
langchain_openai/llms/base.py
langchain_openai/middleware/__init__.py
langchain_openai/middleware/openai_moderation.py
langchain_openai/output_parsers/__init__.py
langchain_openai/output_parsers/tools.py
langchain_openai/tools/__init__.py
langchain_openai/tools/custom_tool.py
langchain_openai-1.1.2.dist-info/METADATA
langchain_openai-1.1.2.dist-info/WHEEL
langchain_openai-1.1.2.dist-info/licenses/LICENSE
langchain_openai-1.1.2.dist-info/RECORD
