Metadata-Version: 2.4
Name: langchain-openai
Version: 1.1.2
Summary: An integration package connecting OpenAI and LangChain
Project-URL: Homepage, https://docs.langchain.com/oss/python/integrations/providers/openai
Project-URL: Documentation, https://reference.langchain.com/python/integrations/langchain_openai/
Project-URL: Source, https://github.com/langchain-ai/langchain/tree/master/libs/partners/openai
Project-URL: Changelog, https://github.com/langchain-ai/langchain/releases?q=%22langchain-openai%22
Project-URL: Twitter, https://x.com/LangChainAI
Project-URL: Slack, https://www.langchain.com/join-community
Project-URL: Reddit, https://www.reddit.com/r/LangChain/
License: MIT
License-File: LICENSE
Requires-Python: <4.0.0,>=3.10.0
Requires-Dist: langchain-core<2.0.0,>=1.1.3
Requires-Dist: openai<3.0.0,>=1.109.1
Requires-Dist: tiktoken<1.0.0,>=0.7.0
